peakrdl_markdown/__init__.py
peakrdl_markdown/__peakrdl__.py
peakrdl_markdown/exporter.py
peakrdl_markdown-1.0.3.dist-info/METADATA
peakrdl_markdown-1.0.3.dist-info/WHEEL
peakrdl_markdown-1.0.3.dist-info/entry_points.txt
peakrdl_markdown-1.0.3.dist-info/licenses/LICENSE
peakrdl_markdown-1.0.3.dist-info/RECORD
