Metadata-Version: 2.4
Name: peakrdl_markdown
Version: 1.0.3
Summary: Export Markdown description from the systemrdl-compiler register model
License: GPL-3.0-only
License-File: LICENSE
Author: Marek Pikuła
Author-email: marek@serenitycode.dev
Maintainer: Marek Pikuła
Maintainer-email: marek@serenitycode.dev
Requires-Python: >=3.7.0,<4.0.0
Classifier: Development Status :: 5 - Production/Stable
Classifier: Intended Audience :: Developers
Classifier: License :: OSI Approved :: GNU General Public License v3 (GPLv3)
Classifier: Operating System :: OS Independent
Classifier: Programming Language :: Python :: 3
Classifier: Programming Language :: Python :: 3.7
Classifier: Programming Language :: Python :: 3.8
Classifier: Programming Language :: Python :: 3.9
Classifier: Programming Language :: Python :: 3.10
Classifier: Programming Language :: Python :: 3.11
Classifier: Programming Language :: Python :: 3.12
Classifier: Programming Language :: Python :: 3.13
Classifier: Programming Language :: Python :: 3.14
Classifier: Topic :: Scientific/Engineering :: Electronic Design Automation (EDA)
Requires-Dist: peakrdl-cli (>=1.5.0,<2.0.0)
Requires-Dist: py-markdown-table (<1.0.0) ; python_version < "3.8"
Requires-Dist: py-markdown-table (>=1.3.0,<2.0.0) ; python_version >= "3.8"
Requires-Dist: systemrdl-compiler (>=1.30.1,<2.0.0)
Project-URL: Documentation, https://peakrdl-markdown.readthedocs.io
Project-URL: Repository, https://github.com/SystemRDL/PeakRDL-Markdown
